animeapi/__init__.py
animeapi/__version__.py
animeapi/animeapi.py
animeapi/asyncaniapi.py
animeapi/base.py
animeapi/converter.py
animeapi/excepts.py
animeapi/models.py
animeapi_py-3.7.1.dist-info/licenses/LICENSE
animeapi_py-3.7.1.dist-info/METADATA
animeapi_py-3.7.1.dist-info/WHEEL
animeapi_py-3.7.1.dist-info/top_level.txt
animeapi_py-3.7.1.dist-info/RECORD
