Metadata-Version: 2.4
Name: animeapi-py
Version: 3.7.1
Summary: A Python wrapper for the AnimeAPI by nattadasu with type hints and additional async support.
Author-email: nattadasu <hello@nattadasu.my.id>
License: AGPL-3.0-or-later
Project-URL: Source, https://github.com/nattadasu/animeapi-py
Project-URL: Bug Tracker, https://github.com/nattadasu/animeapi-py/issues
Project-URL: Homepage, https://animeapi.my.id
Keywords: anime,api,wrapper,async,python,animeapi,nattadasu,relations,mappings,type hints,type annotations
Classifier: Development Status :: 5 - Production/Stable
Classifier: Intended Audience :: Developers
Classifier: License :: OSI Approved :: GNU Affero General Public License v3 or later (AGPLv3+)
Classifier: Operating System :: OS Independent
Classifier: Programming Language :: Python :: 3
Classifier: Programming Language :: Python :: 3 :: Only
Classifier: Programming Language :: Python :: 3.7
Classifier: Programming Language :: Python :: 3.8
Classifier: Programming Language :: Python :: 3.9
Classifier: Programming Language :: Python :: 3.10
Classifier: Programming Language :: Python :: 3.11
Classifier: Programming Language :: Python :: 3.12
Classifier: Typing :: Typed
Requires-Python: >=3.7
License-File: LICENSE
Requires-Dist: requests
Requires-Dist: aiohttp
Requires-Dist: dacite
Requires-Dist: typing-extensions; python_version < "3.8"
Dynamic: license-file
